two1/__init__.py
two1/cli.py
two1/util.py
two1/bitcoin/__init__.py
two1/bitcoin/block.py
two1/bitcoin/coinbase.py
two1/bitcoin/crypto.py
two1/bitcoin/exceptions.py
two1/bitcoin/hash.py
two1/bitcoin/script.py
two1/bitcoin/script_interpreter.py
two1/bitcoin/txn.py
two1/bitcoin/utils.py
two1/bitrequests/__init__.py
two1/bitrequests/bitrequests.py
two1/bitrequests/docs/README.md
two1/bitrequests/docs/bitrequests.png
two1/bitserv/README.md
two1/bitserv/__init__.py
two1/bitserv/models.py
two1/bitserv/payment_methods.py
two1/bitserv/payment_server.py
two1/bitserv/django/README.md
two1/bitserv/django/__init__.py
two1/bitserv/django/decorator.py
two1/bitserv/django/models.py
two1/bitserv/django/urls.py
two1/bitserv/django/views.py
two1/bitserv/django/migrations/0001_initial.py
two1/bitserv/django/migrations/__init__.py
two1/bitserv/flask/README.md
two1/bitserv/flask/__init__.py
two1/bitserv/flask/decorator.py
two1/blockchain/__init__.py
two1/blockchain/base_provider.py
two1/blockchain/exceptions.py
two1/blockchain/insight_provider.py
two1/blockchain/mock_provider.py
two1/blockchain/twentyone_provider.py
two1/channels/__init__.py
two1/channels/blockchain.py
two1/channels/cli.py
two1/channels/database.py
two1/channels/paymentchannel.py
two1/channels/paymentchannelclient.py
two1/channels/server.py
two1/channels/statemachine.py
two1/channels/walletwrapper.py
two1/channels/docs/PCs.png
two1/channels/docs/README.md
two1/channels/docs/channel-logic.txt
two1/channels/docs/rest-handshake-402.txt
two1/channels/docs/rest-handshake-channel.txt
two1/commands/__init__.py
two1/commands/buy.py
two1/commands/channels.py
two1/commands/config.py
two1/commands/doctor.py
two1/commands/earn.py
two1/commands/faucet.py
two1/commands/flush.py
two1/commands/help.py
two1/commands/inbox.py
two1/commands/join.py
two1/commands/log.py
two1/commands/login.py
two1/commands/market.py
two1/commands/mine.py
two1/commands/profile.py
two1/commands/publish.py
two1/commands/rate.py
two1/commands/search.py
two1_fork-3.11.1.dist-info/METADATA
two1_fork-3.11.1.dist-info/WHEEL
two1_fork-3.11.1.dist-info/licenses/LICENSE
two1_fork-3.11.1.dist-info/RECORD
