Metadata-Version: 2.4
Name: two1-fork
Version: 3.11.1
Summary: two1-fork
Project-URL: repository, https://github.com/xuchaoqian/two1-fork.git
Author: https://github.com/21dotco/two1-python
Maintainer-email: Xu Chaoqian <chaoranxu@gmail.com>
License: Copyright (c) 2015-2017, 21 Inc.
License-File: LICENSE
Keywords: 21 commands,bitcoin
Classifier: License :: OSI Approved :: MIT License
Classifier: Operating System :: OS Independent
Classifier: Programming Language :: Python :: 3
Requires-Python: >=3.7
Requires-Dist: arrow==0.6.0
Requires-Dist: base58==0.2.2
Requires-Dist: click==8.2.1
Requires-Dist: docker-py==1.8.0
Requires-Dist: flake8==7.2.0
Requires-Dist: future==0.17.1
Requires-Dist: mnemonic==0.13
Requires-Dist: packaging==25.0
Requires-Dist: pbkdf2==1.3
Requires-Dist: protobuf==3.20
Requires-Dist: pyaes==1.3.0
Requires-Dist: pyyaml==6.0.2
Requires-Dist: requests==2.32.3
Requires-Dist: sha256==1.0
Requires-Dist: tabulate==0.7.5
Provides-Extra: test
Requires-Dist: pytest-asyncio>=0.23.6; extra == 'test'
Requires-Dist: pytest-cov>=4.1.0; extra == 'test'
Requires-Dist: pytest>=8.1.1; extra == 'test'
